chess_schema/__init__.py
chess_schema/base.py
chess_schema/enums.py
chess_schema/game.py
chess_schema/move.py
chess_schema-0.1.4.dist-info/METADATA
chess_schema-0.1.4.dist-info/WHEEL
chess_schema-0.1.4.dist-info/licenses/LICENSE
chess_schema-0.1.4.dist-info/RECORD
