Metadata-Version: 2.4
Name: chess-schema
Version: 0.1.4
Summary: Pydantic models for structured chess game data, optimized for LLM integration and analysis pipelines
Project-URL: Homepage, https://github.com/danieljames-dj/chess-schema
Project-URL: Documentation, https://github.com/danieljames-dj/chess-schema#readme
Project-URL: Repository, https://github.com/danieljames-dj/chess-schema
Project-URL: Issues, https://github.com/danieljames-dj/chess-schema/issues
Project-URL: Changelog, https://github.com/danieljames-dj/chess-schema/releases
Author-email: Daniel James <djdany444@gmail.com>
License: MIT
License-File: LICENSE
Keywords: analysis,chess,llm,pgn,pydantic,san,schema,uci,validation
Classifier: Development Status :: 4 - Beta
Classifier: Intended Audience :: Developers
Classifier: License :: OSI Approved :: MIT License
Classifier: Programming Language :: Python :: 3
Classifier: Programming Language :: Python :: 3.9
Classifier: Programming Language :: Python :: 3.10
Classifier: Programming Language :: Python :: 3.11
Classifier: Programming Language :: Python :: 3.12
Classifier: Topic :: Games/Entertainment :: Board Games
Classifier: Topic :: Software Development :: Libraries :: Python Modules
Classifier: Typing :: Typed
Requires-Python: >=3.9
Requires-Dist: pydantic>=2.0.0
Provides-Extra: dev
Requires-Dist: mypy>=1.0.0; extra == 'dev'
Requires-Dist: pytest-cov>=4.0.0; extra == 'dev'
Requires-Dist: pytest>=7.0.0; extra == 'dev'
Requires-Dist: python-chess>=1.999; extra == 'dev'
Requires-Dist: ruff>=0.1.0; extra == 'dev'
Provides-Extra: pgn
Requires-Dist: python-chess>=1.999; extra == 'pgn'
